kapil_operands/__init__.py
kapil_operands-0.1.dist-info/METADATA
kapil_operands-0.1.dist-info/WHEEL
kapil_operands-0.1.dist-info/top_level.txt
kapil_operands-0.1.dist-info/RECORD
